{
    "tareas": [
        {
            "titulo": "Hacer bugfix mayuscula",
            "responsable": "Mark",
            "descripcion": "lorem ipsum",
            "prioridad": "baja"
        },
        {
            "titulo": "Mock up navegacion",
            "responsable": "Mark",
            "descripcion": "lorem ipsum",
            "prioridad": "alta"
        },
        {
            "titulo": "Preparar conferencia",
            "responsable": "Sara",
            "descripcion": "lorem ipsum",
            "prioridad": "media"
        },
        {
            "titulo": "Traer Cafe",
            "responsable": "Jimmy",
            "descripcion": "Suministrar cafe para todo el equipo siempre que sea necesario",
            "prioridad": "muy alta"
        }
    ]
}